pyround/__init__.py
pyround/main.py
pyround-0.1.0.dist-info/LICENSE.txt
pyround-0.1.0.dist-info/WHEEL
pyround-0.1.0.dist-info/METADATA
pyround-0.1.0.dist-info/RECORD
