Metadata-Version: 2.1
Name: pyround
Version: 0.1.0
Summary: PYPI package with only 1 function to round float numbers to the number of significant digits
Author: stanislav
Author-email: stas.prokopiev@gmail.com
Requires-Python: >=3.6
Classifier: Programming Language :: Python :: 3
Classifier: Programming Language :: Python :: 3.10
Classifier: Programming Language :: Python :: 3.6
Classifier: Programming Language :: Python :: 3.7
Classifier: Programming Language :: Python :: 3.8
Classifier: Programming Language :: Python :: 3.9
